seaborn/seaborn_table.py
seaborn_table-1.1.0.dist-info/DESCRIPTION.rst
seaborn_table-1.1.0.dist-info/METADATA
seaborn_table-1.1.0.dist-info/RECORD
seaborn_table-1.1.0.dist-info/WHEEL
seaborn_table-1.1.0.dist-info/metadata.json
seaborn_table-1.1.0.dist-info/top_level.txt
